EzStore/__init__.py
EzStore/EzStore.py
ezstore-0.1.4.dist-info/LICENSE
ezstore-0.1.4.dist-info/WHEEL
ezstore-0.1.4.dist-info/METADATA
ezstore-0.1.4.dist-info/RECORD
