Metadata-Version: 2.1
Name: ezstore
Version: 0.1.4
Summary: 
Author: Roni Sundstrom
Author-email: ronttipontti.sundstrom2@gmail.com
Requires-Python: >=3.7,<4.0
Classifier: Programming Language :: Python :: 3
Classifier: Programming Language :: Python :: 3.7
Classifier: Programming Language :: Python :: 3.8
Classifier: Programming Language :: Python :: 3.9
Requires-Dist: cryptography (>=3.4.7,<4.0.0)
